LICENSE.txt
README.md
pyproject.toml
camera_ui_sdk/__init__.py
camera_ui_sdk/py.typed
camera_ui_sdk/types.py
camera_ui_sdk/utils.py
camera_ui_sdk.egg-info/PKG-INFO
camera_ui_sdk.egg-info/SOURCES.txt
camera_ui_sdk.egg-info/dependency_links.txt
camera_ui_sdk.egg-info/requires.txt
camera_ui_sdk.egg-info/top_level.txt
camera_ui_sdk/camera/__init__.py
camera_ui_sdk/manager/__init__.py
camera_ui_sdk/observable/__init__.py
camera_ui_sdk/observable/hybrid_observable.py
camera_ui_sdk/plugin/__init__.py
camera_ui_sdk/plugin/api.py
camera_ui_sdk/plugin/contract.py
camera_ui_sdk/plugin/helper.py
camera_ui_sdk/plugin/interfaces.py
camera_ui_sdk/sensor/__init__.py
camera_ui_sdk/sensor/audio.py
camera_ui_sdk/sensor/base.py
camera_ui_sdk/sensor/battery.py
camera_ui_sdk/sensor/classifier.py
camera_ui_sdk/sensor/contact.py
camera_ui_sdk/sensor/doorbell.py
camera_ui_sdk/sensor/face.py
camera_ui_sdk/sensor/license_plate.py
camera_ui_sdk/sensor/light.py
camera_ui_sdk/sensor/motion.py
camera_ui_sdk/sensor/object.py
camera_ui_sdk/sensor/ptz.py
camera_ui_sdk/sensor/security_system.py
camera_ui_sdk/sensor/siren.py
camera_ui_sdk/sensor/spec.py
camera_ui_sdk/sensor/switch.py
camera_ui_sdk/storage/__init__.py