Metadata-Version: 2.4
Name: camera-ui-sdk
Version: 1.0.42
Summary: camera.ui sdk
Author-email: seydx <dev@seydx.com>
Maintainer-email: seydx <dev@seydx.com>
Project-URL: Homepage, https://github.com/seydx/camera.ui
Project-URL: Documentation, https://github.com/seydx/camera.ui
Project-URL: Repository, https://github.com/seydx/camera.ui
Project-URL: Bug Tracker, https://github.com/seydx/camera.ui/issues
Project-URL: Changelog, https://github.com/seydx/camera.ui/blob/master/CHANGELOG.md
Keywords: camera.ui,python,sdk
Classifier: Development Status :: 5 - Production/Stable
Classifier: Intended Audience :: Developers
Classifier: Operating System :: OS Independent
Classifier: Programming Language :: Python :: 3
Classifier: Programming Language :: Python :: 3.11
Classifier: Programming Language :: Python :: 3.12
Classifier: Programming Language :: Python :: 3.13
Requires-Python: >=3.11
License-File: LICENSE.txt
Requires-Dist: typing_extensions>=4.15.0
Requires-Dist: reactivex>=4.1.0
Dynamic: license-file
